diploma_generator/__init__.py
diploma_generator/font.ttf
diploma_generator/main.py
diploma_generator-1.0.2.dist-info/LICENSE
diploma_generator-1.0.2.dist-info/METADATA
diploma_generator-1.0.2.dist-info/WHEEL
diploma_generator-1.0.2.dist-info/entry_points.txt
diploma_generator-1.0.2.dist-info/top_level.txt
diploma_generator-1.0.2.dist-info/RECORD
