Metadata-Version: 2.1
Name: diploma-generator
Version: 1.0.2
Summary: Generate diplomas using images and CSV Files
Home-page: UNKNOWN
Author: Andrés Alonzo
License: UNKNOWN
Platform: UNKNOWN
Classifier: Programming Language :: Python :: 3
Classifier: License :: OSI Approved :: GNU General Public License v3 (GPLv3)
Classifier: Operating System :: OS Independent
Requires-Python: >=3.7
Requires-Dist: fpdf ==1.7.2
